niaclass/__init__.py
niaclass/feature_info.py
niaclass/niaclass.py
niaclass/rule.py
niaclass-0.2.4.dist-info/LICENSE
niaclass-0.2.4.dist-info/METADATA
niaclass-0.2.4.dist-info/WHEEL
niaclass-0.2.4.dist-info/RECORD
