Metadata-Version: 2.1
Name: niaclass
Version: 0.2.4
Summary: Python framework for building classifiers using nature-inspired algorithms
Home-page: https://github.com/firefly-cpp/NiaClass
License: MIT
Keywords: classification,machine learning,NiaPy,nature-inspired algorithms,optimization
Author: Luka Pečnik
Author-email: lukapecnik96@gmail.com
Requires-Python: >=3.9,<3.14
Classifier: License :: OSI Approved :: MIT License
Classifier: Programming Language :: Python :: 3
Classifier: Programming Language :: Python :: 3.9
Classifier: Programming Language :: Python :: 3.10
Classifier: Programming Language :: Python :: 3.11
Classifier: Programming Language :: Python :: 3.12
Classifier: Programming Language :: Python :: 3.13
Requires-Dist: niapy (>=2.5.2,<3.0.0)
Requires-Dist: numpy (>=1.26.1,<2.0.0)
Requires-Dist: pandas (>=2.1.1,<3.0.0)
Requires-Dist: scikit-learn (>=1.6.1,<2.0.0)
Project-URL: Repository, https://github.com/firefly-cpp/NiaClass
